lucien_magic/__init__.py
lucien_magic-0.1.0.dist-info/METADATA
lucien_magic-0.1.0.dist-info/WHEEL
lucien_magic-0.1.0.dist-info/RECORD
