Metadata-Version: 2.4
Name: lucien-magic
Version: 0.1.0
Summary: Lucien jupyter magic
Author-email: todd zhang <toddzhang@pathintegral.xyz>
Requires-Python: >=3.10
Requires-Dist: jsonrpc>=3.0.1
